rtl_sim/fx2.v
/************************************************************************************************
*  Name         :fx2.v
*  Description  :fx2 usb for ADC
*  Origin       :200321
*  Author       :helrori2011@gmail.com
************************************************************************************************/
`define EP2_NOTHING  (cy_flaga==1'd0)//flaga fixed mode,PC->FPGA st_out
`define EP6_FULL     (cy_flagb==1'd0)//flagb fixed mode,FPGA->PC st_in
`define EP2_ADDRESS  (2'b00)
`define EP6_ADDRESS  (2'b10)
`define CYUSB_DELAY  (32'd20000000)//上电延迟,实际测试使用32'd20000000
module fx2
(
   input    wire            clk         ,        
   input    wire            clk_180     ,    //from pll,for FX2 slave fifo write clk
   input    wire            rst_n       ,
   //fifo   
   input    wire            up_req      ,
   output   wire            up_grant    ,
   input    wire    [15:0]  up_dat      ,    //prefetch
   output   reg             up_fin      ,

   output   reg             dn_val      ,
   output   reg     [15:0]  dn_dat      ,
   //cyusb outside
   inout    wire    [15:0]  cy_data     ,
   output   reg     [1 :0]  cy_addr     ,
   output   reg             cy_slrd_n   ,
   output   reg             cy_slwr_n   ,
   output   reg             cy_pkend_n  ,
   output   reg             cy_sloe_n   ,
   input    wire            cy_flaga    ,
   input    wire            cy_flagb    ,
   output   wire            cy_ifclk    ,
   output   reg             cy_ifclk_ok

);
//----------------------------------------------------------------------------------------------
reg             up_req_b;
reg     [31:0]  dly;
reg     [8 :0]  send_cnt;
reg     [3 :0]  cst,nst;
reg             read_en;
wire    [15:0]  cy_data_o;

localparam  DLY         = 0 ,
            REC_CHK     = 1 ,

            RD_BEG      = 2 ,
            RD_SLO      = 3 ,
            RD_NOW      = 4 ,
            RD_END      = 5 ,

            WR_BEG      = 6 ,
            WR_NOW      = 7 ,
            WR_PKE      = 8 ,
            WR_END      = 9 ,

            UP_FIN      = 10 ;


//----------------------------------------------------------------------------------------------
assign   cy_ifclk  = clk_180;
assign   cy_data   = (cy_slwr_n)?16'bz:cy_data_o;//cy_data默认高阻，仅当上载时接上cy_data_o
assign   up_grant  = ~cy_slwr_n;
assign   cy_data_o = up_dat;
always@(posedge clk_180 or negedge rst_n)begin if(!rst_n) cy_ifclk_ok <= 1'd0; else cy_ifclk_ok <= 1'd1;end

always@(posedge clk or negedge rst_n)begin if(!rst_n) cst  <= DLY; else cst  <= nst;end

always@(*)begin
    nst = cst;
    case(cst)
        DLY:begin       // 上电延迟
            nst = (dly >= `CYUSB_DELAY)?REC_CHK:DLY;
        end
        REC_CHK:begin   // 检查进入该模块的数据
            if ( !`EP2_NOTHING ) begin
                nst = RD_BEG;
            end else if( up_req_b && (!`EP6_FULL) )begin
                nst = WR_BEG;
            end
        end
        //--------------------------------------------------------------------------------------
        RD_BEG:begin     // 提早输出地址
            nst = RD_SLO;
        end
        RD_SLO:begin     // 提早将sloe_n置低
            nst = RD_NOW;
        end
        RD_NOW:begin     // 读512bytes
            nst = (send_cnt >= 9'd256)?RD_END:RD_NOW;
        end
        RD_END:begin   
            nst =  REC_CHK;
        end
        //--------------------------------------------------------------------------------------
        WR_BEG:begin
            nst = WR_NOW;
        end
        WR_NOW:begin    // 写512bytes
            nst = (send_cnt >= 9'd256)?WR_PKE:WR_NOW;
        end
        WR_PKE:begin       
            nst = WR_END;
        end
        WR_END:begin
            nst = UP_FIN;
        end
        UP_FIN:begin
            nst = REC_CHK;
        end
        //--------------------------------------------------------------------------------------        
        default:nst = DLY;
    endcase
end

always@(posedge clk or negedge rst_n)begin
    if(!rst_n)begin
        dly            <= 32'd0;
        send_cnt       <= 9'd0;
        cy_addr        <= `EP2_ADDRESS;
        cy_slrd_n      <= 1;
        cy_sloe_n      <= 1;
        cy_slwr_n      <= 1;
        cy_pkend_n     <= 1;
        up_fin         <= 0;
    end else case(nst)
        DLY:begin
            dly     <= dly + 1'd1;
        end
        REC_CHK:begin
            dly     <= 32'd0;
        end
        //--------------------------------------------------------------------------------------
        RD_BEG:begin             
            cy_addr <= `EP2_ADDRESS;
        end
        RD_SLO:begin
            cy_sloe_n   <= 0;
        end        
        RD_NOW:begin//读512bytes
            cy_slrd_n   <= 0;
            send_cnt    <= send_cnt + 1'd1;
        end
        RD_END:begin               
            send_cnt    <= 9'd0;
            cy_slrd_n   <= 1;
            cy_sloe_n   <= 1;
        end
        //--------------------------------------------------------------------------------------
        WR_BEG:begin               
            cy_addr     <= `EP6_ADDRESS;
        end
        WR_NOW:begin//写512bytes
            cy_slwr_n   <= 0;
            send_cnt    <= send_cnt + 1'd1;
        end
        WR_PKE:begin  
            send_cnt    <= 9'd0;        
            cy_slwr_n   <= 1;
            cy_pkend_n  <= 1;//not use
        end
        WR_END:begin                
            cy_pkend_n  <= 1;
            up_fin      <= 1;
        end
        UP_FIN:begin
            up_fin      <= 0;
        end
        //--------------------------------------------------------------------------------------
        default:;
    endcase
end

always@(posedge clk or negedge rst_n)begin
    if(!rst_n)begin
        up_req_b   <= 'd0;
    end else begin
        if(up_fin)
            up_req_b<=  1'd0;       //任务完成，撤回请求
        else if(up_req)begin
            up_req_b<=  1'd1;       //保存请求
        end else
            up_req_b<=  up_req_b;
    end
end

always@(posedge clk_180 or negedge rst_n)begin
    if(!rst_n)begin
        read_en <= 1'd0;
    end else if(cst == RD_SLO && nst == RD_NOW)begin
        read_en <= 1'd1;
    end else if(cst == RD_NOW && nst == RD_END)begin
        read_en <= 1'd0;
    end else read_en <= read_en ;
end
always@(posedge clk or negedge rst_n)begin
    if(!rst_n)begin
        dn_dat <= 16'd0;
        dn_val <=  1'd0;
    end else if(read_en)begin
        dn_dat <= cy_data;
        dn_val <= 1'd1;
    end else begin
        dn_dat <= dn_dat;
        dn_val <= 1'd0;
    end 
    
end



endmodule

rtl_sim/fx2_tb.v
`timescale 1 ns / 1 ps
`define TT 10 
module fx2_tb();
reg clk,rst_n,cy_flaga,cy_flagb,out_en;
wire clk_180,cy_pkend_n,cy_slrd_n,cy_slwr_n,cy_sloe_n,cy_ifclk;
wire [1:0]cy_addr;
reg [15:0]men[7:0];
reg [2:0]cnt;
wire  [15:0]cy_data;
assign cy_data = (!cy_sloe_n)?men[cnt]:16'dz;
initial begin
    $dumpfile("wave.vcd");              //for iverilog gtkwave.exe
    $dumpvars(0,fx2_tb);          //for iverilog select signal 
    cnt    = 'd0; 
    men[0] = {"O","L"};
    men[1] = {"D","P"};
    men[2] = {8'd1,8'd0};
    men[3] = {8'd0,8'd0};
    men[4] = {8'd0,8'd0};
    men[5] = {8'd0,8'd0};
    men[6] = {8'd0,8'd0};
    men[7] = {8'd0,8'hFF};
    clk   = 1;
    rst_n = 1;
    cy_flaga = 0;
    cy_flagb = 1;
    #(`TT*5) rst_n = 0; #(`TT*4) rst_n = 1;
    #(`TT*100)
        
    #(`TT/2) cy_flaga = 1; #(`TT*5) cy_flaga = 0; 
    #(`TT*400)
    
    #(`TT*500)
    cy_flaga = 1; #(`TT*5) cy_flaga = 0;    
    #(`TT*1000)
    
    cy_flaga = 1; #(`TT*5) cy_flaga = 0;    
    #(`TT*1000)
    
    $finish;
end
always begin #(`TT/2) clk = ~clk; end
assign clk_180 = ~clk;


always@(posedge cy_ifclk)begin
    if(cy_slrd_n==0)
        cnt <= cnt +1'd1;
end

wire clk_div4,data_input_en,data_output_valid;
wire [63:0]data_64_in,reg0,data_64_out;

wire dn_val;
wire [15:0]dn_dat;
reg up_req=0;
wire up_grant;
reg [15:0]up_dat=16'h0;
wire up_fin;

always@(posedge clk)begin
    if ( up_fin ) begin
        up_req <= 0;
    end else if(cnt=='d1) begin
        up_req <= 1;
    end
end
always@(posedge clk)begin
    if ( up_grant ) begin
        up_dat <= up_dat + 1;
    end
end
fx2 usb
(
   .clk(clk),        //from pll,The same clock as the ADC
   .clk_180(clk_180),    //from pll,for FX2 slave fifo write clk
   .rst_n(rst_n),
   //cyusb outside
   .cy_data(cy_data),
   .cy_addr(cy_addr),
   .cy_slrd_n(cy_slrd_n),
   .cy_slwr_n(cy_slwr_n),
   .cy_pkend_n(cy_pkend_n),
   .cy_sloe_n(cy_sloe_n),
   .cy_flaga(cy_flaga),
   .cy_flagb(cy_flagb),
   .cy_ifclk(cy_ifclk),
   .cy_ifclk_ok(),
   
   .up_req      ( up_req ),
   .up_grant    ( up_grant ),
   .up_dat      ( up_dat ),    //prefetch
   .up_fin      ( up_fin ),

   .dn_val      ( dn_val ),
   .dn_dat      ( dn_dat )

   
);
endmodule

sim/fx2_tb/wave.vcd
$date
	Mon May 01 14:18:18 2023
$end
$version
	Icarus Verilog
$end
$timescale
	1ps
$end
$scope module fx2_tb $end
$var wire 1 ! clk_180 $end
$var wire 16 " cy_data [15:0] $end
$var wire 1 # up_grant $end
$var wire 1 $ up_fin $end
$var wire 1 % dn_val $end
$var wire 16 & dn_dat [15:0] $end
$var wire 1 ' cy_slwr_n $end
$var wire 1 ( cy_slrd_n $end
$var wire 1 ) cy_sloe_n $end
$var wire 1 * cy_pkend_n $end
$var wire 1 + cy_ifclk $end
$var wire 2 , cy_addr [1:0] $end
$var reg 1 - clk $end
$var reg 3 . cnt [2:0] $end
$var reg 1 / cy_flaga $end
$var reg 1 0 cy_flagb $end
$var reg 1 1 rst_n $end
$var reg 16 2 up_dat [15:0] $end
$var reg 1 3 up_req $end
$scope module usb $end
$var wire 1 - clk $end
$var wire 1 ! clk_180 $end
$var wire 16 4 cy_data [15:0] $end
$var wire 16 5 cy_data_o [15:0] $end
$var wire 1 / cy_flaga $end
$var wire 1 0 cy_flagb $end
$var wire 1 + cy_ifclk $end
$var wire 1 1 rst_n $end
$var wire 16 6 up_dat [15:0] $end
$var wire 1 # up_grant $end
$var wire 1 3 up_req $end
$var reg 4 7 cst [3:0] $end
$var reg 2 8 cy_addr [1:0] $end
$var reg 1 9 cy_ifclk_ok $end
$var reg 1 * cy_pkend_n $end
$var reg 1 ) cy_sloe_n $end
$var reg 1 ( cy_slrd_n $end
$var reg 1 ' cy_slwr_n $end
$var reg 32 : dly [31:0] $end
$var reg 16 ; dn_dat [15:0] $end
$var reg 1 % dn_val $end
$var reg 4 < nst [3:0] $end
$var reg 1 = read_en $end
$var reg 9 > send_cnt [8:0] $end
$var reg 1 $ up_fin $end
$var reg 1 ? up_req_b $end
$upscope $end
$upscope $end
$enddefinitions $end
#0
$dumpvars
x?
bx >
x=
b0 <
bx ;
bx :
x9
bx 8
bx 7
b0 6
b0 5
bx 4
03
b0 2
11
10
0/
b0 .
1-
bx ,
0+
x*
x)
x(
x'
bx &
0%
x$
x#
bx "
0!
$end
#5000
19
1+
1!
0-
#10000
b0x <
b0 7
0+
0!
1-
#15000
1+
1!
0-
#20000
b0 <
b0x 7
0+
0!
1-
#25000
1+
1!
0-
#30000
b0x <
b0 7
0+
0!
1-
#35000
1+
1!
0-
#40000
b0 <
b0x 7
0+
0!
1-
#45000
1+
1!
0-
#50000
bz "
bz 4
0#
b0 &
b0 ;
0?
0$
1*
1'
1)
1(
b0 ,
b0 8
b0 >
b0 :
b0 7
0=
09
0+
0!
1-
01
#55000
1+
1!
0-
#60000
0+
0!
1-
#65000
1+
1!
0-
#70000
0+
0!
1-
#75000
1+
1!
0-
#80000
0+
0!
1-
#85000
1+
1!
0-
#90000
b1 :
0+
0!
1-
11
#95000
19
1+
1!
0-
#100000
b10 :
0+
0!
1-
#105000
1+
1!
0-
#110000
b11 :
0+
0!
1-
#115000
1+
1!
0-
#120000
b100 :
0+
0!
1-
#125000
1+
1!
0-
#130000
b101 :
0+
0!
1-
#135000
1+
1!
0-
#140000
b110 :
0+
0!
1-
#145000
1+
1!
0-
#150000
b111 :
0+
0!
1-
#155000
1+
1!
0-
#160000
b1000 :
0+
0!
1-
#165000
1+
1!
0-
#170000
b1001 :
0+
0!
1-
#175000
1+
1!
0-
#180000
b1010 :
0+
0!
1-
#185000
1+
1!
0-
#190000
b1011 :
0+
0!
1-
#195000
1+
1!
0-
#200000
b1100 :
0+
0!
1-
#205000
1+
1!
0-
#210000
b1101 :
0+
0!
1-
#215000
1+
1!
0-
#220000
b1110 :
0+
0!
1-
#225000
1+
1!
0-
#230000
b1111 :
0+
0!
1-
#235000
1+
1!
0-
#240000
b10000 :
0+
0!
1-
#245000
1+
1!
0-
#250000
b10001 :
0+
0!
1-
#255000
1+
1!
0-
#260000
b10010 :
0+
0!
1-
#265000
1+
1!
0-
#270000
b10011 :
0+
0!
1-
#275000
1+
1!
0-
#280000
b10100 :
0+
0!
1-
#285000
1+
1!
0-
#290000
b10101 :
0+
0!
1-
#295000
1+
1!
0-
#300000
b10110 :
0+
0!
1-
#305000
1+
1!
0-
#310000
b10111 :
0+
0!
1-
#315000
1+
1!
0-
#320000
b11000 :
0+
0!
1-
#325000
1+
1!
0-
#330000
b11001 :
0+
0!
1-
#335000
1+
1!
0-
#340000
b11010 :
0+
0!
1-
#345000
1+
1!
0-
#350000
b11011 :
0+
0!
1-
#355000
1+
1!
0-
#360000
b11100 :
0+
0!
1-
#365000
1+
1!
0-
#370000
b11101 :
0+
0!
1-
#375000
1+
1!
0-
#380000
b11110 :
0+
0!
1-
#385000
1+
1!
0-
#390000
b11111 :
0+
0!
1-
#395000
1+
1!
0-
#400000
b100000 :
0+
0!
1-
#405000
1+
1!
0-
#410000
b100001 :
0+
0!
1-
#415000
1+
1!
0-
#420000
b100010 :
0+
0!
1-
#425000
1+
1!
0-
#430000
b100011 :
0+
0!
1-
#435000
1+
1!
0-
#440000
b100100 :
0+
0!
1-
#445000
1+
1!
0-
#450000
b100101 :
0+
0!
1-
#455000
1+
1!
0-
#460000
b100110 :
0+
0!
1-
#465000
1+
1!
0-
#470000
b100111 :
0+
0!
1-
#475000
1+
1!
0-
#480000
b101000 :
0+
0!
1-
#485000
1+
1!
0-
#490000
b101001 :
0+
0!
1-
#495000
1+
1!
0-
#500000
b101010 :
0+
0!
1-
#505000
1+
1!
0-
#510000
b101011 :
0+
0!
1-
#515000
1+
1!
0-
#520000
b101100 :
0+
0!
1-
#525000
1+
1!
0-
#530000
b101101 :
0+
0!
1-
#535000
1+
1!
0-
#540000
b101110 :
0+
0!
1-
#545000
1+
1!
0-
#550000
b101111 :
0+
0!
1-
#555000
1+
1!
0-
#560000
b110000 :
0+
0!
1-
#565000
1+
1!
0-
#570000
b110001 :
0+
0!
1-
#575000
1+
1!
0-
#580000
b110010 :
0+
0!
1-
#585000
1+
1!
0-
#590000
b110011 :
0+
0!
1-
#595000
1+
1!
0-
#600000
b110100 :
0+
0!
1-
#605000
1+
1!
0-
#610000
b110101 :
0+
0!
1-
#615000
1+
1!
0-
#620000
b110110 :
0+
0!
1-
#625000
1+
1!
0-
#630000
b110111 :
0+
0!
1-
#635000
1+
1!
0-
#640000
b111000 :
0+
0!
1-
#645000
1+
1!
0-
#650000
b111001 :
0+
0!
1-
#655000
1+
1!
0-
#660000
b111010 :
0+
0!
1-
#665000
1+
1!
0-
#670000
b111011 :
0+
0!
1-
#675000
1+
1!
0-
#680000
b111100 :
0+
0!
1-
#685000
1+
1!
0-
#690000
b111101 :
0+
0!
1-
#695000
1+
1!
0-
#700000
b111110 :
0+
0!
1-
#705000
1+
1!
0-
#710000
b111111 :
0+
0!
1-
#715000
1+
1!
0-
#720000
b1000000 :
0+
0!
1-
#725000
1+
1!
0-
#730000
b1000001 :
0+
0!
1-
#735000
1+
1!
0-
#740000
b1000010 :
0+
0!
1-
#745000
1+
1!
0-
#750000
b1000011 :
0+
0!
1-
#755000
1+
1!
0-
#760000
b1000100 :
0+
0!
1-
#765000
1+
1!
0-
#770000
b1000101 :
0+
0!
1-
#775000
1+
1!
0-
#780000
b1000110 :
0+
0!
1-
#785000
1+
1!
0-
#790000
b1000111 :
0+
0!
1-
#795000
1+
1!
0-
#800000
b1001000 :
0+
0!
1-
#805000
1+
1!
0-
#810000
b1001001 :
0+
0!
1-
#815000
1+
1!
0-
#820000
b1001010 :
0+
0!
1-
#825000
1+
1!
0-
#830000
b1001011 :
0+
0!
1-
#835000
1+
1!
0-
#840000
b1001100 :
0+
0!
1-
#845000
1+
1!
0-
#850000
b1001101 :
0+
0!
1-
#855000
1+
1!
0-
#860000
b1001110 :
0+
0!
1-
#865000
1+
1!
0-
#870000
b1001111 :
0+
0!
1-
#875000
1+
1!
0-
#880000
b1010000 :
0+
0!
1-
#885000
1+
1!
0-
#890000
b1010001 :
0+
0!
1-
#895000
1+
1!
0-
#900000
b1010010 :
0+
0!
1-
#905000
1+
1!
0-
#910000
b1010011 :
0+
0!
1-
#915000
1+
1!
0-
#920000
b1010100 :
0+
0!
1-
#925000
1+
1!
0-
#930000
b1010101 :
0+
0!
1-
#935000
1+
1!
0-
#940000
b1010110 :
0+
0!
1-
#945000
1+
1!
0-
#950000
b1010111 :
0+
0!
1-
#955000
1+
1!
0-
#960000
b1011000 :
0+
0!
1-
#965000
1+
1!
0-
#970000
b1011001 :
0+
0!
1-
#975000
1+
1!
0-
#980000
b1011010 :
0+
0!
1-
#985000
1+
1!
0-
#990000
b1011011 :
0+
0!
1-
#995000
1+
1!
0-
#1000000
b1011100 :
0+
0!
1-
#1005000
1+
1!
0-
#1010000
b1011101 :
0+
0!
1-
#1015000
1+
1!
0-
#1020000
b1011110 :
0+
0!
1-
#1025000
1+
1!
0-
#1030000
b1011111 :
0+
0!
1-
#1035000
1+
1!
0-
#1040000
b1100000 :
0+
0!
1-
#1045000
1+
1!
0-
#1050000
b1100001 :
0+
0!
1-
#1055000
1+
1!
0-
#1060000
b1100010 :
0+
0!
1-
#1065000
1+
1!
0-
#1070000
b1100011 :
0+
0!
1-
#1075000
1+
1!
0-
#1080000
b1100100 :
0+
0!
1-
#1085000
1+
1!
0-
#1090000
b1100101 :
0+
0!
1-
#1095000
1+
1!
0-
1/
#1100000
b1100110 :
0+
0!
1-
#1105000
1+
1!
0-
#1110000
b1100111 :
0+
0!
1-
#1115000
1+
1!
0-
#1120000
b1101000 :
0+
0!
1-
#1125000
1+
1!
0-
#1130000
b1101001 :
0+
0!
1-
#1135000
1+
1!
0-
#1140000
b1101010 :
0+
0!
1-
#1145000
1+
1!
0-
0/
#1150000
b1101011 :
0+
0!
1-
#1155000
1+
1!
0-
#1160000
b1101100 :
0+
0!
1-
#1165000
1+
1!
0-
#1170000
b1101101 :
0+
0!
1-
#1175000
1+
1!
0-
#1180000
b1101110 :
0+
0!
1-
#1185000
1+
1!
0-
#1190000
b1101111 :
0+
0!
1-
#1195000
1+
1!
0-
#1200000
b1110000 :
0+
0!
1-
#1205000
1+
1!
0-
#1210000
b1110001 :
0+
0!
1-
#1215000
1+
1!
0-
#1220000
b1110010 :
0+
0!
1-
#1225000
1+
1!
0-
#1230000
b1110011 :
0+
0!
1-
#1235000
1+
1!
0-
#1240000
b1110100 :
0+
0!
1-
#1245000
1+
1!
0-
#1250000
b1110101 :
0+
0!
1-
#1255000
1+
1!
0-
#1260000
b1110110 :
0+
0!
1-
#1265000
1+
1!
0-
#1270000
b1110111 :
0+
0!
1-
#1275000
1+
1!
0-
#1280000
b1111000 :
0+
0!
1-
#1285000
1+
1!
0-
#1290000
b1111001 :
0+
0!
1-
#1295000
1+
1!
0-
#1300000
b1111010 :
0+
0!
1-
#1305000
1+
1!
0-
#1310000
b1111011 :
0+
0!
1-
#1315000
1+
1!
0-
#1320000
b1111100 :
0+
0!
1-
#1325000
1+
1!
0-
#1330000
b1111101 :
0+
0!
1-
#1335000
1+
1!
0-
#1340000
b1111110 :
0+
0!
1-
#1345000
1+
1!
0-
#1350000
b1111111 :
0+
0!
1-
#1355000
1+
1!
0-
#1360000
b10000000 :
0+
0!
1-
#1365000
1+
1!
0-
#1370000
b10000001 :
0+
0!
1-
#1375000
1+
1!
0-
#1380000
b10000010 :
0+
0!
1-
#1385000
1+
1!
0-
#1390000
b10000011 :
0+
0!
1-
#1395000
1+
1!
0-
#1400000
b10000100 :
0+
0!
1-
#1405000
1+
1!
0-
#1410000
b10000101 :
0+
0!
1-
#1415000
1+
1!
0-
#1420000
b10000110 :
0+
0!
1-
#1425000
1+
1!
0-
#1430000
b10000111 :
0+
0!
1-
#1435000
1+
1!
0-
#1440000
b10001000 :
0+
0!
1-
#1445000
1+
1!
0-
#1450000
b10001001 :
0+
0!
1-
#1455000
1+
1!
0-
#1460000
b10001010 :
0+
0!
1-
#1465000
1+
1!
0-
#1470000
b10001011 :
0+
0!
1-
#1475000
1+
1!
0-
#1480000
b10001100 :
0+
0!
1-
#1485000
1+
1!
0-
#1490000
b10001101 :
0+
0!
1-
#1495000
1+
1!
0-
#1500000
b10001110 :
0+
0!
1-
#1505000
1+
1!
0-
#1510000
b10001111 :
0+
0!
1-
#1515000
1+
1!
0-
#1520000
b10010000 :
0+
0!
1-
#1525000
1+
1!
0-
#1530000
b10010001 :
0+
0!
1-
#1535000
1+
1!
0-
#1540000
b10010010 :
0+
0!
1-
#1545000
1+
1!
0-
#1550000
b10010011 :
0+
0!
1-
#1555000
1+
1!
0-
#1560000
b10010100 :
0+
0!
1-
#1565000
1+
1!
0-
#1570000
b10010101 :
0+
0!
1-
#1575000
1+
1!
0-
#1580000
b10010110 :
0+
0!
1-
#1585000
1+
1!
0-
#1590000
b10010111 :
0+
0!
1-
#1595000
1+
1!
0-
#1600000
b10011000 :
0+
0!
1-
#1605000
1+
1!
0-
#1610000
b10011001 :
0+
0!
1-
#1615000
1+
1!
0-
#1620000
b10011010 :
0+
0!
1-
#1625000
1+
1!
0-
#1630000
b10011011 :
0+
0!
1-
#1635000
1+
1!
0-
#1640000
b10011100 :
0+
0!
1-
#1645000
1+
1!
0-
#1650000
b10011101 :
0+
0!
1-
#1655000
1+
1!
0-
#1660000
b10011110 :
0+
0!
1-
#1665000
1+
1!
0-
#1670000
b10011111 :
0+
0!
1-
#1675000
1+
1!
0-
#1680000
b10100000 :
0+
0!
1-
#1685000
1+
1!
0-
#1690000
b10100001 :
0+
0!
1-
#1695000
1+
1!
0-
#1700000
b10100010 :
0+
0!
1-
#1705000
1+
1!
0-
#1710000
b10100011 :
0+
0!
1-
#1715000
1+
1!
0-
#1720000
b10100100 :
0+
0!
1-
#1725000
1+
1!
0-
#1730000
b10100101 :
0+
0!
1-
#1735000
1+
1!
0-
#1740000
b10100110 :
0+
0!
1-
#1745000
1+
1!
0-
#1750000
b10100111 :
0+
0!
1-
#1755000
1+
1!
0-
#1760000
b10101000 :
0+
0!
1-
#1765000
1+
1!
0-
#1770000
b10101001 :
0+
0!
1-
#1775000
1+
1!
0-
#1780000
b10101010 :
0+
0!
1-
#1785000
1+
1!
0-
#1790000
b10101011 :
0+
0!
1-
#1795000
1+
1!
0-
#1800000
b10101100 :
0+
0!
1-
#1805000
1+
1!
0-
#1810000
b10101101 :
0+
0!
1-
#1815000
1+
1!
0-
#1820000
b10101110 :
0+
0!
1-
#1825000
1+
1!
0-
#1830000
b10101111 :
0+
0!
1-
#1835000
1+
1!
0-
#1840000
b10110000 :
0+
0!
1-
#1845000
1+
1!
0-
#1850000
b10110001 :
0+
0!
1-
#1855000
1+
1!
0-
#1860000
b10110010 :
0+
0!
1-
#1865000
1+
1!
0-
#1870000
b10110011 :
0+
0!
1-
#1875000
1+
1!
0-
#1880000
b10110100 :
0+
0!
1-
#1885000
1+
1!
0-
#1890000
b10110101 :
0+
0!
1-
#1895000
1+
1!
0-
#1900000
b10110110 :
0+
0!
1-
#1905000
1+
1!
0-
#1910000
b10110111 :
0+
0!
1-
#1915000
1+
1!
0-
#1920000
b10111000 :
0+
0!
1-
#1925000
1+
1!
0-
#1930000
b10111001 :
0+
0!
1-
#1935000
1+
1!
0-
#1940000
b10111010 :
0+
0!
1-
#1945000
1+
1!
0-
#1950000
b10111011 :
0+
0!
1-
#1955000
1+
1!
0-
#1960000
b10111100 :
0+
0!
1-
#1965000
1+
1!
0-
#1970000
b10111101 :
0+
0!
1-
#1975000
1+
1!
0-
#1980000
b10111110 :
0+
0!
1-
#1985000
1+
1!
0-
#1990000
b10111111 :
0+
0!
1-
#1995000
1+
1!
0-
#2000000
b11000000 :
0+
0!
1-
#2005000
1+
1!
0-
#2010000
b11000001 :
0+
0!
1-
#2015000
1+
1!
0-
#2020000
b11000010 :
0+
0!
1-
#2025000
1+
1!
0-
#2030000
b11000011 :
0+
0!
1-
#2035000
1+
1!
0-
#2040000
b11000100 :
0+
0!
1-
#2045000
1+
1!
0-
#2050000
b11000101 :
0+
0!
1-
#2055000
1+
1!
0-
#2060000
b11000110 :
0+
0!
1-
#2065000
1+
1!
0-
#2070000
b11000111 :
0+
0!
1-
#2075000
1+
1!
0-
#2080000
b11001000 :
0+
0!
1-
#2085000
1+
1!
0-
#2090000
b11001001 :
0+
0!
1-
#2095000
1+
1!
0-
#2100000
b11001010 :
0+
0!
1-
#2105000
1+
1!
0-
#2110000
b11001011 :
0+
0!
1-
#2115000
1+
1!
0-
#2120000
b11001100 :
0+
0!
1-
#2125000
1+
1!
0-
#2130000
b11001101 :
0+
0!
1-
#2135000
1+
1!
0-
#2140000
b11001110 :
0+
0!
1-
#2145000
1+
1!
0-
#2150000
b11001111 :
0+
0!
1-
#2155000
1+
1!
0-
#2160000
b11010000 :
0+
0!
1-
#2165000
1+
1!
0-
#2170000
b11010001 :
0+
0!
1-
#2175000
1+
1!
0-
#2180000
b11010010 :
0+
0!
1-
#2185000
1+
1!
0-
#2190000
b11010011 :
0+
0!
1-
#2195000
1+
1!
0-
#2200000
b11010100 :
0+
0!
1-
#2205000
1+
1!
0-
#2210000
b11010101 :
0+
0!
1-
#2215000
1+
1!
0-
#2220000
b11010110 :
0+
0!
1-
#2225000
1+
1!
0-
#2230000
b11010111 :
0+
0!
1-
#2235000
1+
1!
0-
#2240000
b11011000 :
0+
0!
1-
#2245000
1+
1!
0-
#2250000
b11011001 :
0+
0!
1-
#2255000
1+
1!
0-
#2260000
b11011010 :
0+
0!
1-
#2265000
1+
1!
0-
#2270000
b11011011 :
0+
0!
1-
#2275000
1+
1!
0-
#2280000
b11011100 :
0+
0!
1-
#2285000
1+
1!
0-
#2290000
b11011101 :
0+
0!
1-
#2295000
1+
1!
0-
#2300000
b11011110 :
0+
0!
1-
#2305000
1+
1!
0-
#2310000
b11011111 :
0+
0!
1-
#2315000
1+
1!
0-
#2320000
b11100000 :
0+
0!
1-
#2325000
1+
1!
0-
#2330000
b11100001 :
0+
0!
1-
#2335000
1+
1!
0-
#2340000
b11100010 :
0+
0!
1-
#2345000
1+
1!
0-
#2350000
b11100011 :
0+
0!
1-
#2355000
1+
1!
0-
#2360000
b11100100 :
0+
0!
1-
#2365000
1+
1!
0-
#2370000
b11100101 :
0+
0!
1-
#2375000
1+
1!
0-
#2380000
b11100110 :
0+
0!
1-
#2385000
1+
1!
0-
#2390000
b11100111 :
0+
0!
1-
#2395000
1+
1!
0-
#2400000
b11101000 :
0+
0!
1-
#2405000
1+
1!
0-
#2410000
b11101001 :
0+
0!
1-
#2415000
1+
1!
0-
#2420000
b11101010 :
0+
0!
1-
#2425000
1+
1!
0-
#2430000
b11101011 :
0+
0!
1-
#2435000
1+
1!
0-
#2440000
b11101100 :
0+
0!
1-
#2445000
1+
1!
0-
#2450000
b11101101 :
0+
0!
1-
#2455000
1+
1!
0-
#2460000
b11101110 :
0+
0!
1-
#2465000
1+
1!
0-
#2470000
b11101111 :
0+
0!
1-
#2475000
1+
1!
0-
#2480000
b11110000 :
0+
0!
1-
#2485000
1+
1!
0-
#2490000
b11110001 :
0+
0!
1-
#2495000
1+
1!
0-
#2500000
b11110010 :
0+
0!
1-
#2505000
1+
1!
0-
#2510000
b11110011 :
0+
0!
1-
#2515000
1+
1!
0-
#2520000
b11110100 :
0+
0!
1-
#2525000
1+
1!
0-
#2530000
b11110101 :
0+
0!
1-
#2535000
1+
1!
0-
#2540000
b11110110 :
0+
0!
1-
#2545000
1+
1!
0-
#2550000
b11110111 :
0+
0!
1-
#2555000
1+
1!
0-
#2560000
b11111000 :
0+
0!
1-
#2565000
1+
1!
0-
#2570000
b11111001 :
0+
0!
1-
#2575000
1+
1!
0-
#2580000
b11111010 :
0+
0!
1-
#2585000
1+
1!
0-
#2590000
b11111011 :
0+
0!
1-
#2595000
1+
1!
0-
#2600000
b11111100 :
0+
0!
1-
#2605000
1+
1!
0-
#2610000
b11111101 :
0+
0!
1-
#2615000
1+
1!
0-
#2620000
b11111110 :
0+
0!
1-
#2625000
1+
1!
0-
#2630000
b11111111 :
0+
0!
1-
#2635000
1+
1!
0-
#2640000
b100000000 :
0+
0!
1-
#2645000
1+
1!
0-
#2650000
b100000001 :
0+
0!
1-
#2655000
1+
1!
0-
#2660000
b100000010 :
0+
0!
1-
#2665000
1+
1!
0-
#2670000
b100000011 :
0+
0!
1-
#2675000
1+
1!
0-
#2680000
b100000100 :
0+
0!
1-
#2685000
1+
1!
0-
#2690000
b100000101 :
0+
0!
1-
#2695000
1+
1!
0-
#2700000
b100000110 :
0+
0!
1-
#2705000
1+
1!
0-
#2710000
b100000111 :
0+
0!
1-
#2715000
1+
1!
0-
#2720000
b100001000 :
0+
0!
1-
#2725000
1+
1!
0-
#2730000
b100001001 :
0+
0!
1-
#2735000
1+
1!
0-
#2740000
b100001010 :
0+
0!
1-
#2745000
1+
1!
0-
#2750000
b100001011 :
0+
0!
1-
#2755000
1+
1!
0-
#2760000
b100001100 :
0+
0!
1-
#2765000
1+
1!
0-
#2770000
b100001101 :
0+
0!
1-
#2775000
1+
1!
0-
#2780000
b100001110 :
0+
0!
1-
#2785000
1+
1!
0-
#2790000
b100001111 :
0+
0!
1-
#2795000
1+
1!
0-
#2800000
b100010000 :
0+
0!
1-
#2805000
1+
1!
0-
#2810000
b100010001 :
0+
0!
1-
#2815000
1+
1!
0-
#2820000
b100010010 :
0+
0!
1-
#2825000
1+
1!
0-
#2830000
b100010011 :
0+
0!
1-
#2835000
1+
1!
0-
